__init__.py
ass2rythmo.py
fonts/DejaVuSans.ttf
ass2rythmo-1.0.0.dist-info/LICENSE
ass2rythmo-1.0.0.dist-info/LICENSE-dejavu.txt
ass2rythmo-1.0.0.dist-info/METADATA
ass2rythmo-1.0.0.dist-info/WHEEL
ass2rythmo-1.0.0.dist-info/entry_points.txt
ass2rythmo-1.0.0.dist-info/top_level.txt
ass2rythmo-1.0.0.dist-info/RECORD
