Metadata-Version: 2.1
Name: ass2rythmo
Version: 1.0.0
Summary: Generate rythmo band from Ass subtitles
Author-email: Olivier Jolly <olivier@pcedev.com>
License: GPLv3+
Project-URL: Homepage, https://gitlab.com/zeograd/ass2rythmo
Project-URL: Bug Tracker, https://gitlab.com/zeograd/ass2rythmo/-/issues
Keywords: ass rythmo subtitles subs
Classifier: Development Status :: 5 - Production/Stable
Classifier: Environment :: Console
Classifier: Topic :: Multimedia :: Sound/Audio
Classifier: Topic :: Multimedia :: Video
Classifier: License :: OSI Approved :: GNU General Public License v3 or later (GPLv3+)
Classifier: Programming Language :: Python :: 3
Classifier: Operating System :: OS Independent
Classifier: Development Status :: 4 - Beta
Requires-Python: >=3.2
License-File: LICENSE
License-File: LICENSE-dejavu.txt
Requires-Dist: numpy
Requires-Dist: freetype-py
Requires-Dist: pillow
Requires-Dist: attrs >=18.2.0
Requires-Dist: progressbar2
